<?xml version="1.0"?>
<base>
	<History>
		<PreviousPath>h:\program files\nival interactive\bk-resource_pack\units\technics\allies\auto\ford_pick-up\current.msh</PreviousPath>
		<PreviousDate>19.09.2008</PreviousDate>
		<PreviousTime>20:29:24</PreviousTime>
		<PreviousOwner>Administrator</PreviousOwner>
		<Action>Exported as</Action>
		<CurrentPath>h:\units\technics\allies\auto\ford_pick-up\1.xml</CurrentPath>
		<CurrentDate>19.09.2008</CurrentDate>
		<CurrentTime>20:30:11</CurrentTime>
		<CurrentOwner>Administrator</CurrentOwner>
	</History>
	<RPG MaxHP="80" RepairCost="1" Sight="32" SightPower="1" Speed="18" Passability="0.07" Priority="1" Camouflage="4" Weight="1480" Price="1" UninstallRotate="0" UninstallTransport="0" RotateSpeed="44" TurnRadius="5" TowingForce="600" Crew="2" Passangers="6" BoundTileRadius="1" SmallAABBCoeff="1" TowPoint="7" EntrancePoint="-1" FatalitySmokePoint="-1" ShootDustPoint="-1" LeavesTracks="1" TrackOffset="0.15" TrackWidth="0.15" TrackStart="0.2" TrackEnd="0.2" TrackIntensity="0.7" TrackLifetime="10000" MaxHeight="500" DivingAngle="20" ClimbAngle="20" TiltAngle="30" TiltRatio="2">
		<KeyName>Ford Pck-Up</KeyName>
		<StatsType>Mech</StatsType>
		<DamagedHPs/>
		<Defence0 MinArmor="40" MaxArmor="90" Silhouette="1"/>
		<Defence1 MinArmor="40" MaxArmor="90" Silhouette="1"/>
		<Defence2 MinArmor="40" MaxArmor="90" Silhouette="1"/>
		<Defence3 MinArmor="40" MaxArmor="90" Silhouette="1"/>
		<Defence4 MinArmor="40" MaxArmor="90" Silhouette="1"/>
		<Defence5 MinArmor="40" MaxArmor="90" Silhouette="1"/>
		<Type>trn_carrier</Type>
		<AIClass>wheel</AIClass>
		<Commands Size="40">
			<BitArray>
				<item data="33"/>
				<item data="3"/>
				<item data="128"/>
				<item data="128"/>
				<item data="129"/>
				<item data="0"/>
				<item data="4"/>
			</BitArray>
		</Commands>
		<Exposures Size="5">
			<BitArray>
				<item data="16"/>
			</BitArray>
		</Exposures>
		<AnimDescs>
			<item>
				<data/>
			</item>
			<item>
				<data/>
			</item>
			<item>
				<data/>
			</item>
			<item>
				<data/>
			</item>
			<item>
				<data/>
			</item>
			<item>
				<data/>
			</item>
			<item>
				<data/>
			</item>
			<item>
				<data/>
			</item>
			<item>
				<data/>
			</item>
			<item>
				<data>
					<item Length="625" Action="0" Index="0" AABB_A="-1" AABB_D="-1"/>
				</data>
			</item>
			<item>
				<data/>
			</item>
			<item>
				<data/>
			</item>
			<item>
				<data/>
			</item>
			<item>
				<data/>
			</item>
			<item>
				<data/>
			</item>
			<item>
				<data/>
			</item>
			<item>
				<data/>
			</item>
			<item>
				<data/>
			</item>
			<item>
				<data/>
			</item>
			<item>
				<data/>
			</item>
			<item>
				<data/>
			</item>
			<item>
				<data/>
			</item>
			<item>
				<data/>
			</item>
			<item>
				<data/>
			</item>
			<item>
				<data/>
			</item>
			<item>
				<data/>
			</item>
			<item>
				<data/>
			</item>
			<item>
				<data/>
			</item>
			<item>
				<data/>
			</item>
			<item>
				<data/>
			</item>
			<item>
				<data/>
			</item>
		</AnimDescs>
		<AABB_As/>
		<AABB_Ds/>
		<AcksRefs>
			<item></item>
		</AcksRefs>
		<AcksRef/>
		<Platforms>
			<item VerticalRotateSpeed="10" HorizontalRotationSpeed="60" ModelPart="4" GunCarriageParts="-1" FirstGun="0" NumGuns="0">
				<Constraint Min="0" Max="0"/>
				<ConstraintVertical Min="0" Max="0"/>
			</item>
			<item VerticalRotateSpeed="10" HorizontalRotationSpeed="60" ModelPart="-1" GunCarriageParts="-1" FirstGun="0" NumGuns="0">
				<Constraint Min="0" Max="0"/>
				<ConstraintVertical Min="0" Max="0"/>
			</item>
		</Platforms>
		<Guns/>
		<ArmorLeft Min="1" Max="1"/>
		<ArmorRight Min="1" Max="1"/>
		<ArmorTop Min="1" Max="1"/>
		<ArmorBottom Min="1" Max="1"/>
		<ArmorFront Min="1" Max="2"/>
		<ArmorBack Min="1" Max="1"/>
		<AABBCenter x="7.34329e-005" y="1.78242"/>
		<AABBHalfSize x="14.5297" y="36.4354"/>
		<ExhaustPoints>
			<item data="8"/>
			<item data="8"/>
		</ExhaustPoints>
		<DamagePoints>
			<item data="9"/>
		</DamagePoints>
		<PeoplePoints/>
		<TowPoint2D x="0" y="-38.4332"/>
		<HookPoint x="0" y="0"/>
		<FrontWheel x="0" y="0"/>
		<BackWheel x="0" y="0"/>
		<EntrancePoint2D x="0" y="0"/>
		<PeoplePoints2D/>
		<AmmoPoint2D x="0" y="0"/>
		<Gunners>
			<item>
				<data/>
			</item>
			<item>
				<data/>
			</item>
			<item>
				<data/>
			</item>
		</Gunners>
		<EffectDiesel>smokedisel1</EffectDiesel>
		<EffectSmoke>smokeflame2lit</EffectSmoke>
		<EffectWheelDust>dustmove1</EffectWheelDust>
		<EffectShootDust/>
		<EffectFatality>expfatality2lit</EffectFatality>
		<EffectEntrenching/>
		<EffectDisappear>brakedown2</EffectDisappear>
		<JoggingX Period1="1.6" Period2="0.6" Amp1="0.5" Amp2="0.3" Phase1="0" Phase2="2.1"/>
		<JoggingY Period1="1.1" Period2="0.3" Amp1="0.6" Amp2="0.2" Phase1="1.9" Phase2="0"/>
		<JoggingZ Period1="1" Period2="0.3" Amp1="1" Amp2="0.6" Phase1="0" Phase2="2.1"/>
		<SoundMoveStart>Auto1_start</SoundMoveStart>
		<SoundMove>Auto6_cycle</SoundMove>
		<SoundMoveStop>Auto1_stop</SoundMoveStop>
		<DeathCraters>
			<item>objects\terraobjects\death_hole\verybig\01\1</item>
			<item>objects\terraobjects\death_hole\verybig\02\1</item>
			<item>objects\terraobjects\death_hole\verybig\03\1</item>
		</DeathCraters>
	</RPG>
</base>
