<?xml version="1.0"?>
<base><History><PreviousPath>d:\b\complete\units\technics\common\t_26e\current.msh</PreviousPath><PreviousDate>9.04.2005</PreviousDate><PreviousTime>17:54:49</PreviousTime><PreviousOwner>Bk-Tools :: Unit Editor [version 1.0.2]</PreviousOwner><Action>Exported as</Action><CurrentPath>d:\program files\nival interactive\blitzkrieg\mods\mymod\data\units\technics\ussr\tanks\t_26e\1.xml</CurrentPath><CurrentDate>9.04.2005</CurrentDate><CurrentTime>17:57:55</CurrentTime><CurrentOwner>Bk-Tools :: Unit Editor [version 1.0.2]</CurrentOwner></History><RPG MaxHP="130" RepairCost="3" Sight="35" SightPower="1.4" Speed="7.89" Passability="0.3" Priority="1" Camouflage="4" Weight="10300" Price="1.03" UninstallRotate="0" UninstallTransport="0" RotateSpeed="20" TurnRadius="5" TowingForce="0" Crew="3" Passangers="0" BoundTileRadius="1" SmallAABBCoeff="0.85" TowPoint="15" EntrancePoint="14" FatalitySmokePoint="16" ShootDustPoint="-1" LeavesTracks="1" TrackOffset="0" TrackWidth="0.1" TrackStart="0.2" TrackEnd="0.2" TrackIntensity="0.7" TrackLifetime="10000" MaxHeight="500" DivingAngle="20" ClimbAngle="20" TiltAngle="30" TiltRatio="2"><KeyName>T-26E</KeyName><StatsType>Mech</StatsType><DamagedHPs/><Defence0 MinArmor="40" MaxArmor="90" Silhouette="1"/><Defence1 MinArmor="40" MaxArmor="90" Silhouette="1"/><Defence2 MinArmor="40" MaxArmor="90" Silhouette="1"/><Defence3 MinArmor="40" MaxArmor="90" Silhouette="1"/><Defence4 MinArmor="40" MaxArmor="90" Silhouette="1"/><Defence5 MinArmor="40" MaxArmor="90" Silhouette="1"/><Type>arm_light</Type><AIClass>track</AIClass><Commands Size="51"><BitArray><item data="47"/><item data="67"/><item data="0"/><item data="0"/><item data="128"/><item data="32"/><item data="4"/></BitArray></Commands><Exposures Size="5"><BitArray><item data="16"/></BitArray></Exposures><AnimDescs><item><data/></item><item><data/></item><item><data/></item><item><data/></item><item><data/></item><item><data/></item><item><data/></item><item><data/></item><item><data/></item><item><data><item Length="562" Action="0" Index="0" AABB_A="-1" AABB_D="-1"/><item Length="562" Action="0" Index="1" AABB_A="-1" AABB_D="-1"/><item Length="562" Action="0" Index="2" AABB_A="-1" AABB_D="-1"/><item Length="562" Action="0" Index="3" AABB_A="-1" AABB_D="-1"/><item Length="562" Action="0" Index="4" AABB_A="-1" AABB_D="-1"/><item Length="562" Action="0" Index="5" AABB_A="-1" AABB_D="-1"/></data></item><item><data/></item><item><data/></item><item><data/></item><item><data/></item><item><data/></item><item><data/></item><item><data/></item><item><data/></item><item><data/></item><item><data/></item><item><data/></item><item><data/></item><item><data/></item><item><data><item Length="1187" Action="0" Index="6" AABB_A="0" AABB_D="0"/><item Length="1187" Action="0" Index="7" AABB_A="1" AABB_D="1"/><item Length="1187" Action="0" Index="8" AABB_A="2" AABB_D="2"/><item Length="1187" Action="0" Index="9" AABB_A="3" AABB_D="3"/><item Length="1187" Action="0" Index="10" AABB_A="4" AABB_D="4"/></data></item><item><data/></item><item><data/></item><item><data/></item><item><data/></item><item><data/></item><item><data/></item><item><data/></item></AnimDescs><AABB_As><item><Center x="9.67006" y="1.19452"/><HalfSize x="36.1979" y="40.6751"/></item><item><Center x="5.97748" y="21.6248"/><HalfSize x="27.9654" y="60.739"/></item><item><Center x="18.8089" y="-5.76011"/><HalfSize x="40.009" y="45.5372"/></item><item><Center x="-22.5183" y="0.149376"/><HalfSize x="45.296" y="39.9576"/></item><item><Center x="16.8136" y="0.151747"/><HalfSize x="40.7749" y="39.9221"/></item></AABB_As><AABB_Ds><item><Center x="0.660448" y="1.38042"/><HalfSize x="21.3317" y="39.0612"/></item><item><Center x="-0.566849" y="0.313103"/><HalfSize x="20.6524" y="39.1088"/></item><item><Center x="-2.71949" y="-0.224461"/><HalfSize x="24.4511" y="41.2455"/></item><item><Center x="0.918841" y="-1.6315"/><HalfSize x="22.4872" y="40.423"/></item><item><Center x="-0.634158" y="-0.761961"/><HalfSize x="22.476" y="40.7743"/></item></AABB_Ds><AcksRefs><item>sounds\ack\Finnish\tank</item></AcksRefs><AcksRef></AcksRef><Platforms><item VerticalRotateSpeed="0" HorizontalRotationSpeed="10" ModelPart="1" GunCarriageParts="-1" FirstGun="0" NumGuns="1"><Constraint Min="-0.0375246" Max="0.05044"/><ConstraintVertical Min="0" Max="0"/></item><item VerticalRotateSpeed="0" HorizontalRotationSpeed="5.67" ModelPart="5" GunCarriageParts="-1" FirstGun="1" NumGuns="2"><Constraint Min="-6.28319" Max="6.28319"/><ConstraintVertical Min="0" Max="0"/></item></Platforms><Guns><item Priority="1" Ammo="100" Direction="65535" ReloadCost="1" ShootPoint="17" Recoil="0" RecoilLength="0.0879646" RecoilTime="50" ModelPart="1" RecoilShakeTime="500" RecoilShakeAngle="0"><Weapon>dt7_62</Weapon></item><item Priority="0" Ammo="136" Direction="65535" ReloadCost="257" ShootPoint="19" Recoil="1" RecoilLength="0" RecoilTime="50" ModelPart="6" RecoilShakeTime="400" RecoilShakeAngle="0.0523599"><Weapon>45mm20k</Weapon></item><item Priority="1" Ammo="2848" Direction="65535" ReloadCost="1" ShootPoint="18" Recoil="0" RecoilLength="12.5664" RecoilTime="50" ModelPart="5" RecoilShakeTime="400" RecoilShakeAngle="0.0523599"><Weapon>dt7_62</Weapon></item></Guns><ArmorLeft Min="14" Max="14"/><ArmorRight Min="14" Max="14"/><ArmorTop Min="6" Max="10"/><ArmorBottom Min="6" Max="6"/><ArmorFront Min="14" Max="33"/><ArmorBack Min="14" Max="14"/><AABBCenter x="0.0949402" y="0.383965"/><AABBHalfSize x="19.0363" y="38.6507"/><ExhaustPoints><item data="7"/><item data="8"/></ExhaustPoints><DamagePoints><item data="9"/><item data="10"/><item data="11"/><item data="12"/><item data="13"/></DamagePoints><PeoplePoints/><TowPoint2D x="0" y="-36.2602"/><HookPoint x="0" y="0"/><FrontWheel x="0" y="0"/><BackWheel x="0" y="0"/><EntrancePoint2D x="-17.8295" y="0.100763"/><PeoplePoints2D/><AmmoPoint2D x="0" y="0"/><Gunners><item><data/></item><item><data/></item><item><data/></item></Gunners><EffectDiesel>smokedisel1</EffectDiesel><EffectSmoke>smokeflame2lit</EffectSmoke><EffectWheelDust>dustmove1</EffectWheelDust><EffectShootDust></EffectShootDust><EffectFatality>expfatality2lit</EffectFatality><EffectEntrenching></EffectEntrenching><EffectDisappear>brakedown1</EffectDisappear><JoggingX Period1="1.4" Period2="0.5" Amp1="0.7" Amp2="0.45" Phase1="0" Phase2="2.1"/><JoggingY Period1="1" Period2="0.4" Amp1="0.6" Amp2="0.4" Phase1="1.9" Phase2="0"/><JoggingZ Period1="1" Period2="0.3" Amp1="1" Amp2="0.6" Phase1="0" Phase2="2.1"/><SoundMoveStart>Tank10_custom_start</SoundMoveStart><SoundMove>Tank10_custom_cycle</SoundMove><SoundMoveStop>Tank10_custom_stop</SoundMoveStop><DeathCraters><item>objects\terraobjects\death_hole\big\01\1</item><item>objects\terraobjects\death_hole\big\02\1</item><item>objects\terraobjects\death_hole\big\03\1</item></DeathCraters></RPG></base>
